fellipems_csv_json_converter/__init__.py
fellipems_csv_json_converter/converter.py
fellipems_csv_json_converter-0.1.8.dist-info/entry_points.txt
fellipems_csv_json_converter-0.1.8.dist-info/WHEEL
fellipems_csv_json_converter-0.1.8.dist-info/METADATA
fellipems_csv_json_converter-0.1.8.dist-info/RECORD
