Metadata-Version: 2.1
Name: fellipems-csv-json-converter
Version: 0.1.8
Summary: Curso de introducao ao python: Conversor CSV-JSON
Author: FellipeMS
Author-email: fellipems.sc@gmail.com
Requires-Python: >=3.9,<4.0
Classifier: Programming Language :: Python :: 3
Classifier: Programming Language :: Python :: 3.10
Classifier: Programming Language :: Python :: 3.9
Requires-Dist: click (>=8.0.1,<9.0.0)
Requires-Dist: pandas (>=1.3.3,<2.0.0)
